lims_utils/__init__.py
lims_utils/__main__.py
lims_utils/_version.py
lims_utils/auth.py
lims_utils/database.py
lims_utils/logging.py
lims_utils/models.py
lims_utils/settings.py
lims_utils/tables.py
lims_utils-0.4.9.dist-info/licenses/LICENSE
lims_utils-0.4.9.dist-info/METADATA
lims_utils-0.4.9.dist-info/WHEEL
lims_utils-0.4.9.dist-info/entry_points.txt
lims_utils-0.4.9.dist-info/top_level.txt
lims_utils-0.4.9.dist-info/RECORD
