Metadata-Version: 2.4
Name: lims-utils
Version: 0.4.9
Summary: Commonly used utility functions for Expeye and adjacent projects/APIs.
Author-email: Guilherme de Freitas <guilherme.de-freitas@diamond.ac.uk>
License:                                  Apache License
Project-URL: GitHub, https://github.com/DiamondLightSource/lims-utils
Classifier: Development Status :: 3 - Alpha
Classifier: License :: OSI Approved :: Apache Software License
Classifier: Programming Language :: Python :: 3.9
Classifier: Programming Language :: Python :: 3.10
Classifier: Programming Language :: Python :: 3.11
Requires-Python: >=3.9
License-File: LICENSE
Requires-Dist: SQLAlchemy~=2.0.16
Requires-Dist: pydantic<2.13.0,>=2.8.2
Requires-Dist: fastapi<0.120.0,>=0.104.1
Requires-Dist: pydantic-settings<2.12,>=2.1
Provides-Extra: dev
Requires-Dist: black; extra == "dev"
Requires-Dist: mypy; extra == "dev"
Requires-Dist: pipdeptree; extra == "dev"
Requires-Dist: pre-commit; extra == "dev"
Requires-Dist: pydata-sphinx-theme>=0.12; extra == "dev"
Requires-Dist: pytest; extra == "dev"
Requires-Dist: pytest-cov; extra == "dev"
Requires-Dist: ruff; extra == "dev"
Requires-Dist: sphinx-autobuild; extra == "dev"
Requires-Dist: sphinx-copybutton; extra == "dev"
Requires-Dist: sphinx-design; extra == "dev"
Requires-Dist: tox-direct; extra == "dev"
Requires-Dist: types-mock; extra == "dev"
Requires-Dist: pytest-asyncio; extra == "dev"
Dynamic: license-file
